tests/__init__.py
tests/test_async.py
tests/test_dict.py
tests/test_match.py
tests/test_mock_atts.py
tests/test_mock_class.py
tests/test_mock_methods.py
tests/test_safety.py
tests/test_verify.py
typemock/__init__.py
typemock/_safety.py
typemock/_utils.py
typemock/_verify.py
typemock/api.py
typemock/match.py
typemock/_mock/__init__.py
typemock/_mock/attributes.py
typemock/_mock/methods.py
typemock/_mock/object.py
typemock/_mock/responders.py
typemock-0.5.1.dist-info/LICENSE
typemock-0.5.1.dist-info/METADATA
typemock-0.5.1.dist-info/WHEEL
typemock-0.5.1.dist-info/top_level.txt
typemock-0.5.1.dist-info/RECORD
