Metadata-Version: 2.1
Name: typemock
Version: 0.5.1
Summary: Type safe mocking
Home-page: https://github.com/lgwillmore/type-mock
Author: Laurence Willmore
License: UNKNOWN
Platform: UNKNOWN
Classifier: Development Status :: 3 - Alpha
Classifier: Programming Language :: Python :: 3.5
Classifier: Programming Language :: Python :: 3.6
Classifier: Programming Language :: Python :: 3.7
Classifier: License :: OSI Approved :: MIT License
Classifier: Operating System :: OS Independent
Requires-Dist: typeguard
